pctheory/__init__.py
pctheory/contour.py
pctheory/group.py
pctheory/pcarray.py
pctheory/pcseg.py
pctheory/pcset.py
pctheory/pitch.py
pctheory/pseg.py
pctheory/pset.py
pctheory/set_complex.py
pctheory/tables.py
pctheory/transformations.py
pctheory/util.py
pctheory/data/__init__.py
pctheory/data/all_trichord.json
pctheory/data/babbitt_trichord.json
pctheory/data/eleven_interval.json
pctheory/data/sc12.json
pctheory/data/sc24.json
pctheory/data/ten_trichord.json
pctheory-0.0.44.dist-info/licenses/LICENSE
pctheory-0.0.44.dist-info/METADATA
pctheory-0.0.44.dist-info/WHEEL
pctheory-0.0.44.dist-info/top_level.txt
pctheory-0.0.44.dist-info/RECORD
