Metadata-Version: 2.4
Name: pctheory
Version: 0.0.44
Summary: A package with functionality for atonal music theory
Author-email: Jeffrey Martin <jmartin@jeffreymartincomposer.com>
License-Expression: MIT AND (Apache-2.0 OR BSD-2-Clause)
Project-URL: Homepage, https://fleximeter.github.io/pctheory.html
Classifier: Development Status :: 3 - Alpha
Classifier: Operating System :: OS Independent
Requires-Python: >=3.10
License-File: LICENSE
Requires-Dist: numpy
Requires-Dist: matplotlib
Requires-Dist: networkx
Requires-Dist: pyvis
Dynamic: license-file
